README.md
setup.py
lint_django_migrations/__init__.py
lint_django_migrations/migration_linter.py
lint_django_migrations/sql_analyser.py
lint_django_migrations/state.py
lint_django_migrations/utils.py
lint_django_migrations.egg-info/PKG-INFO
lint_django_migrations.egg-info/SOURCES.txt
lint_django_migrations.egg-info/dependency_links.txt
lint_django_migrations.egg-info/requires.txt
lint_django_migrations.egg-info/top_level.txt
lint_django_migrations/management/__init__.py
lint_django_migrations/management/commands/__init__.py
lint_django_migrations/management/commands/lintmigrations.py
tests/__init__.py
tests/fixtures.py
tests/test_linter.py
tests/test_project/__init__.py
tests/test_project/settings.py
tests/test_project/urls.py
tests/test_project/wsgi.py
tests/test_project/app_add_column_with_default/__init__.py
tests/test_project/app_add_column_with_default/admin.py
tests/test_project/app_add_column_with_default/apps.py
tests/test_project/app_add_column_with_default/models.py
tests/test_project/app_add_column_with_default/tests.py
tests/test_project/app_add_column_with_default/views.py
tests/test_project/app_add_column_with_default/migrations/0001_create_table.py
tests/test_project/app_add_column_with_default/migrations/0002_add_column_with_default_field.py
tests/test_project/app_add_column_with_default/migrations/__init__.py
tests/test_project/app_add_not_null_column/__init__.py
tests/test_project/app_add_not_null_column/admin.py
tests/test_project/app_add_not_null_column/apps.py
tests/test_project/app_add_not_null_column/models.py
tests/test_project/app_add_not_null_column/tests.py
tests/test_project/app_add_not_null_column/views.py
tests/test_project/app_add_not_null_column/migrations/0001_create_table.py
tests/test_project/app_add_not_null_column/migrations/0002_add_new_not_null_field.py
tests/test_project/app_add_not_null_column/migrations/__init__.py
tests/test_project/app_add_not_null_column_followed_by_default/__init__.py
tests/test_project/app_add_not_null_column_followed_by_default/admin.py
tests/test_project/app_add_not_null_column_followed_by_default/apps.py
tests/test_project/app_add_not_null_column_followed_by_default/models.py
