Metadata-Version: 2.1
Name: lint-django-migrations
Version: 1.1.0
Summary: Detect backward incompatible migrations for your django project
Home-page: https://github.com/cedar-team/lint_django_migrations
Author: Cedar
Author-email: support@cedar.com
License: Apache License 2.0
Keywords: django migration lint linter database backward compatibility
Platform: UNKNOWN
Classifier: Development Status :: 4 - Beta
Classifier: Intended Audience :: Developers
Classifier: Environment :: Web Environment
Classifier: Framework :: Django
Classifier: Framework :: Django :: 1.11
Classifier: Framework :: Django :: 2.0
Classifier: Framework :: Django :: 2.1
Classifier: Framework :: Django :: 2.2
Classifier: Programming Language :: Python
Classifier: Programming Language :: Python :: 3.6
Classifier: Programming Language :: Python :: 3.7
Provides-Extra: test
